pdf_approval/__init__.py
pdf_approval/approval_util.py
pdf_approval-0.1.2.dist-info/licenses/LICENSE
pdf_approval-0.1.2.dist-info/METADATA
pdf_approval-0.1.2.dist-info/WHEEL
pdf_approval-0.1.2.dist-info/top_level.txt
pdf_approval-0.1.2.dist-info/RECORD
