Metadata-Version: 2.4
Name: pdf-approval
Version: 0.1.2
Summary: Lightweight PDF approval testing library.
Author-email: Abderrahmen khalledi <abderrahmen.khalledi@gmail.com>
License: MIT License
Project-URL: Homepage, https://github.com/Abderrahmen/pdf-approval
Project-URL: Repository, https://github.com/Abderrahmen/pdf-approval
Keywords: pdf,testing,approval-tests
Classifier: Programming Language :: Python :: 3
Classifier: License :: OSI Approved :: MIT License
Classifier: Operating System :: OS Independent
License-File: LICENSE
Dynamic: license-file
